ppdire/__init__.py
ppdire/_dicomo_utils.py
ppdire/_ppdire_utils.py
ppdire/capi.py
ppdire/dicomo.py
ppdire/ppdire.py
ppdire-0.2.3.dist-info/LICENSE
ppdire-0.2.3.dist-info/METADATA
ppdire-0.2.3.dist-info/WHEEL
ppdire-0.2.3.dist-info/top_level.txt
ppdire-0.2.3.dist-info/RECORD
