Metadata-Version: 2.1
Name: ppdire
Version: 0.2.3
Summary: Projection Pursuit Dimension Reduction
Home-page: https://github.com/SvenSerneels/ppdire
Author: Sven Serneels
Author-email: svenserneels@gmail.com
License: UNKNOWN
Platform: UNKNOWN
Classifier: Programming Language :: Python :: 3
Classifier: License :: OSI Approved :: GNU General Public License v3 or later (GPLv3+)
Classifier: Operating System :: OS Independent
Requires-Dist: numpy (>=1.5.0)
Requires-Dist: scipy (>=0.8.0)
Requires-Dist: matplotlib (>=2.2.0)
Requires-Dist: scikit-learn (>=0.18.0)
Requires-Dist: pandas (>=0.19.0)
Requires-Dist: statsmodels (>=0.8.0)
Requires-Dist: sprm (>=0.3.0)
